{
  "config": {
    "frame": "Diatone/ET-150-V1.0-Carbon-Fiber-Quadcopter",
    "esc": "DYS/Mini-20A",
    "motor": "dys 1104",
    "fc": "AbuseMark/Acro-Naze32",
    "prop": [
      "rotorx  3020"
    ],
    "arm": "",
    "battery": [
      "nano tech 450mah 65-130c 3s"
    ],
    "osd": "ReadyToFlyQuads/Micro-MinimOSD",
    "receiver": "FrSky/D4R-II",
    "flightcam": "MC900DA-V9",
    "hqcam": "808 #16 d lens",
    "videotx": "FT952 5.8GHz 32CH 200MW",
    "blackbox": "",
    "voltagereg": "Pololu D24V6F5, D-sun adjustable"
  },
  "version": 1
}